[
  {
    "number": 1,
    "approved": false,
    "length": "mini",
    "title": "The Case of the Cooperative Alibi",
    "emoji": "🕵️",
    "approxTime": "2-3 min",
    "keywords": ["detective", "alibi", "humor"],
    "chapters": 8,
    "tone": "Humorous",
    "createdWithStoryPipelineVersion": 2.3,
    "revisedWithStoryPipelineVersion": 3.0
  },
  {
    "number": 2,
    "approved": false,
    "length": "medium",
    "title": "Midnight at Hollow Moon Museum",
    "emoji": "🏺",
    "approxTime": "5-7 min",
    "keywords": ["museum", "conspiracy", "paranormal"],
    "chapters": 10,
    "tone": "Suspenseful",
    "createdWithStoryPipelineVersion": 0,
    "revisedWithStoryPipelineVersion": 0
  },
  {
    "number": 3,
    "approved": true,
    "length": "medium",
    "title": "The Quiet Frequency",
    "emoji": "🌊",
    "approxTime": "4-5 min",
    "keywords": ["deep-sea", "signal", "silence"],
    "chapters": 10,
    "tone": "Mysterious",
    "createdWithStoryPipelineVersion": 1.1,
    "revisedWithStoryPipelineVersion": 2.3
  },
  {
    "number": 4,
    "approved": false,
    "length": "medium",
    "title": "The Clockwork Carnival",
    "emoji": "🎠",
    "approxTime": "5-7 min",
    "keywords": ["carnival", "clockwork", "wish"],
    "chapters": 8,
    "tone": "Surreal / Strange",
    "createdWithStoryPipelineVersion": 0,
    "revisedWithStoryPipelineVersion": 0
  },
  {
    "number": 5,
    "approved": false,
    "length": "medium",
    "title": "The Sunken Library",
    "emoji": "🌊",
    "approxTime": "4-7 min",
    "keywords": ["maritime", "forbidden", "trust"],
    "chapters": 13,
    "tone": "Mysterious",
    "createdWithStoryPipelineVersion": 0,
    "revisedWithStoryPipelineVersion": 2.3
  },
  {
    "number": 6,
    "approved": false,
    "length": "medium",
    "title": "Echoes of the Perseid Gate",
    "emoji": "🚀",
    "approxTime": "4-6 min",
    "keywords": ["spaceship", "anomaly", "gate"],
    "chapters": 10,
    "tone": "Epic / Heroic",
    "createdWithStoryPipelineVersion": 0,
    "revisedWithStoryPipelineVersion": 0
  },
  {
    "number": 7,
    "approved": false,
    "length": "medium",
    "title": "Whiskers and the Midnight Key",
    "emoji": "🐈",
    "approxTime": "4-7 min",
    "keywords": ["cat", "attic", "magic"],
    "chapters": 9,
    "tone": "Whimsical",
    "createdWithStoryPipelineVersion": 0,
    "revisedWithStoryPipelineVersion": 2.3
  },
  {
    "number": 8,
    "approved": false,
    "length": "medium",
    "title": "Crown of the Underforge",
    "emoji": "🧙",
    "approxTime": "5-9 min",
    "keywords": ["wizards", "dwarves", "dungeons"],
    "chapters": 9,
    "tone": "Epic / Heroic",
    "createdWithStoryPipelineVersion": 0,
    "revisedWithStoryPipelineVersion": 0
  },
  {
    "number": 9,
    "approved": false,
    "length": "long",
    "title": "The Fracture Hour",
    "emoji": "⏱️",
    "approxTime": "5-8 min",
    "keywords": ["loop", "countdown", "contact"],
    "chapters": 10,
    "tone": "Suspenseful",
    "createdWithStoryPipelineVersion": 1.0,
    "revisedWithStoryPipelineVersion": 2.3
  }
]
